{
  "daus": [
    {
      "BBNDauFlaggedForReplacement": true,
      "BBNDauMonetaryCost": 50000,
      "GloballyUniqueId": "I#86:5",
      "Port": [
        {
          "BBNPortFunctionality": "Bus",
          "Excitation": false,
          "GloballyUniqueId": "I#49:182",
          "PortDirection": "Input"
        },
        {
          "BBNPortFunctionality": "Bus",
          "Excitation": false,
          "GloballyUniqueId": "I#49:183",
          "PortDirection": "Input"
        },
        {
          "BBNPortFunctionality": "SignalConditioning",
          "Excitation": true,
          "GloballyUniqueId": "I#49:176",
          "Measurement": [
            {
              "DataLength": {
                "Min": 16,
                "Max": 16
              },
              "DataRate": {
                "Min": 4000,
                "Max": 4000
              },
              "GloballyUniqueId": "16523944-d5f2-430e-af83-d9b9aab92e50",
              "SampleRate": {
                "Min": 250,
                "Max": 250
              }
            }
          ],
          "PortDirection": "Input",
          "PortType": "SignalConditioner"
        },
        {
          "BBNPortFunctionality": "SignalConditioning",
          "Excitation": true,
          "GloballyUniqueId": "I#49:178",
          "Measurement": [
            {
              "DataLength": {
                "Min": 16,
                "Max": 16
              },
              "DataRate": {
                "Min": 4000,
                "Max": 4000
              },
              "GloballyUniqueId": "27c8b35e-1c91-47d3-b903-15c76619f7de",
              "SampleRate": {
                "Min": 250,
                "Max": 250
              }
            }
          ],
          "PortDirection": "Input",
          "PortType": "SignalConditioner"
        },
        {
          "BBNPortFunctionality": "SignalConditioning",
          "Excitation": true,
          "GloballyUniqueId": "I#49:177",
          "Measurement": [
            {
              "DataLength": {
                "Min": 16,
                "Max": 16
              },
              "DataRate": {
                "Min": 4000,
                "Max": 4000
              },
              "GloballyUniqueId": "916c9208-d59a-4cd8-96c8-2f0a1d70d675",
              "SampleRate": {
                "Min": 250,
                "Max": 250
              }
            }
          ],
          "PortDirection": "Input",
          "PortType": "SignalConditioner"
        },
        {
          "BBNPortFunctionality": "SignalConditioning",
          "Excitation": true,
          "GloballyUniqueId": "I#49:174",
          "Measurement": [
            {
              "DataLength": {
                "Min": 16,
                "Max": 16
              },
              "DataRate": {
                "Min": 4000,
                "Max": 4000
              },
              "GloballyUniqueId": "93cf4c0f-a7f4-4e2d-b37b-e7607851608d",
              "SampleRate": {
                "Min": 250,
                "Max": 250
              }
            }
          ],
          "PortDirection": "Input",
          "PortType": "SignalConditioner"
        },
        {
          "BBNPortFunctionality": "SignalConditioning",
          "Excitation": true,
          "GloballyUniqueId": "I#49:172",
          "Measurement": [
            {
              "DataLength": {
                "Min": 16,
                "Max": 16
              },
              "DataRate": {
                "Min": 4000,
                "Max": 4000
              },
              "GloballyUniqueId": "a1d2f2d7-50b3-4319-bb78-69513c4fb986",
              "SampleRate": {
                "Min": 250,
                "Max": 250
              }
            }
          ],
          "PortDirection": "Input",
          "PortType": "SignalConditioner"
        },
        {
          "BBNPortFunctionality": "SignalConditioning",
          "Excitation": true,
          "GloballyUniqueId": "I#49:173",
          "Measurement": [
            {
              "DataLength": {
                "Min": 16,
                "Max": 16
              },
              "DataRate": {
                "Min": 4000,
                "Max": 4000
              },
              "GloballyUniqueId": "b9abacc0-573b-42c0-9877-8423acb8bd06",
              "SampleRate": {
                "Min": 250,
                "Max": 250
              }
            }
          ],
          "PortDirection": "Input",
          "PortType": "SignalConditioner"
        }
      ]
    }
  ]
}